{
    "chisel": {
        "cargoLocks": null,
        "date": "2025-02-24",
        "extract": null,
        "name": "chisel",
        "passthru": null,
        "pinned": false,
        "src": {
            "deepClone": false,
            "fetchSubmodules": false,
            "leaveDotGit": false,
            "name": null,
            "owner": "chipsalliance",
            "repo": "chisel",
            "rev": "486b55dcaeb5fd32f8c4fc711602920c70cff774",
            "sha256": "sha256-AyFVw2L3JI+nHZUdk2cr0sORh+cIrxmXjTZFedyA/uE=",
            "sparseCheckout": [],
            "type": "github"
        },
        "version": "486b55dcaeb5fd32f8c4fc711602920c70cff774"
    }
}