{
    "chisel": {
        "cargoLocks": null,
        "date": "2025-01-09",
        "extract": null,
        "name": "chisel",
        "passthru": null,
        "pinned": false,
        "src": {
            "deepClone": false,
            "fetchSubmodules": false,
            "leaveDotGit": false,
            "name": null,
            "owner": "unlsycn",
            "repo": "chisel",
            "rev": "ea01f89d39c138bc4c260baf5e8e088e120f4265",
            "sha256": "sha256-KNcAgOA/YBt+1QOVXGpK/33BZ8PpDcHDdAnIBDLfSqI=",
            "type": "github"
        },
        "version": "ea01f89d39c138bc4c260baf5e8e088e120f4265"
    }
}